business_card_qr/__init__.py
business_card_qr/app.py
business_card_qr/qr_generator.py
business_card_qr-0.1.0.dist-info/METADATA
business_card_qr-0.1.0.dist-info/WHEEL
business_card_qr-0.1.0.dist-info/entry_points.txt
business_card_qr-0.1.0.dist-info/top_level.txt
business_card_qr-0.1.0.dist-info/RECORD
