Metadata-Version: 2.4
Name: business-card-qr
Version: 0.1.0
Summary: Generate professional vCard QR codes with custom styling
Author-email: Your Name <your.email@example.com>
License: MIT
Keywords: qr-code,vcard,business-card,qr-generator
Classifier: License :: OSI Approved :: MIT License
Classifier: Programming Language :: Python :: 3
Classifier: Programming Language :: Python :: 3.8
Classifier: Programming Language :: Python :: 3.9
Classifier: Programming Language :: Python :: 3.10
Classifier: Programming Language :: Python :: 3.11
Classifier: Programming Language :: Python :: 3.12
Requires-Python: >=3.8
Requires-Dist: qrcode[pil]>=7.4.2
Requires-Dist: Pillow>=10.0.0
Requires-Dist: streamlit>=1.28.0
